LICENSE
README.md
setup.cfg
setup.py
dwex/__init__.py
dwex/__main__.py
dwex/aftercrash.py
dwex/aranges.py
dwex/cookie.py
dwex/crash.py
dwex/details.py
dwex/die.py
dwex/dwarfone.py
dwex/dwarfutil.py
dwex/exprdlg.py
dwex/exprutil.py
dwex/formats.py
dwex/frames.py
dwex/funcmap.py
dwex/fx.py
dwex/locals.py
dwex/locs.py
dwex/machounwind.py
dwex/patch.py
dwex/ranges.py
dwex/scriptdlg.py
dwex/tree.py
dwex/treedlg.py
dwex/ui.py
dwex/unwind.py
dwex.egg-info/PKG-INFO
dwex.egg-info/SOURCES.txt
dwex.egg-info/dependency_links.txt
dwex.egg-info/entry_points.txt
dwex.egg-info/requires.txt
dwex.egg-info/top_level.txt
test/testall.py
test/testlocal.py